gResistor-3.2.2.data/data/share/applications/gresistor.desktop
gResistor-3.2.2.data/data/share/gresistor/gresistor.glade
gResistor-3.2.2.data/data/share/gresistor/gresistor.png
gResistor-3.2.2.data/data/share/icons/gresistor.png
gresistor3/__init__.py
gresistor3/gresistor.py
gResistor-3.2.2.dist-info/METADATA
gResistor-3.2.2.dist-info/WHEEL
gResistor-3.2.2.dist-info/entry_points.txt
gResistor-3.2.2.dist-info/top_level.txt
gResistor-3.2.2.dist-info/RECORD
