Metadata-Version: 2.1
Name: gResistor
Version: 3.2.2
Summary: Resistor color code calculator
Home-page: https://gresistor.stethewwolf.eu
Author: Stefano Prina
Author-email: stethewwolf@gmail.com
License: GPL
Platform: UNKNOWN
Requires-Python: >=3.8
